UART_emission/RxUnit.vhd
library IEEE;
use IEEE.std_logic_1164.all;

entity RxUnit is
  port (
    clk, reset       : in  std_logic;
    enable           : in  std_logic;
    read             : in  std_logic;
    rxd              : in  std_logic;
    data             : out std_logic_vector(7 downto 0);
    Ferr, OErr, DRdy : out std_logic);
end RxUnit;

architecture RxUnit_arch of RxUnit is
	type tcompteur16 is (idle, waiting, working);				-- type état du compteur 16
	type tcontroleReception is (idlec, workingc, endingc);	-- type état du contrôleur

	signal etat16 : tcompteur16 := idle;							-- état du compteur
	signal tmpRxD : std_logic;
	signal tmpClk : std_logic;
	signal trameEnd : std_logic;										-- permet de signaler la fin de la trame au compteur
	
	signal data_reg : std_logic_vector (7 downto 0);			-- registre pour stocker temporairement les données reçues avant de les envoyer s'il n'y pas d'erreur de parité ou de bit de stop

	signal etatc : tcontroleReception := idlec;					-- état du contrôleur
	signal recep : std_logic;											-- notifier au contrôleur qu'on reçoit de la donnée

begin
	-- Element compteur 16
	process(enable, reset)
		variable cptClk : natural;
	begin
		if (reset = '0') then
			-- Initialisation des signaux
			etat16 <= idle;
			tmpRxD <= '1';
			tmpClk <= '0';
			recep <= '0';

		elsif (rising_edge(enable)) then
			case etat16 is
				when idle =>
					if (rxd = '0') then
						-- Réception bit de start
						cptClk := 8;
						etat16 <= waiting;
						tmpClk <= '0';
					end if;

				when waiting =>
					if (cptClk = 1) then
						-- On a fini d'attendre
						etat16 <= working;
						tmpRxD <= rxd;	-- récupérer la données
						tmpClk <= '1';
						recep <= '1';	-- signaler qu'on commence à recevoir
					else 
						cptClk := cptClk - 1;
					end if;

					if (trameEnd = '1') then 
						-- fin de la reception de la trame
						etat16 <= idle;
						recep <= '0';
					end if;

				when working =>
					-- Repositionner les compteurs
					tmpClk <= '0';
					cptClk := 15;
					etat16 <= waiting;

					if (trameEnd = '1') then 
					-- fin de la reception de la trame 
						etat16 <= idle;
						recep <= '0';
					end if;					
			end case;
		end if;
	end process;

	-- Element controle reception
	process(clk, reset)
		variable cptBit : natural; 
		variable parite_calc : std_logic; -- la parité calculée
		variable parite : std_logic;		 -- bit de parité reçu
		variable stop : std_logic;			 -- bit de stop reçu
	begin
		if (reset = '0') then
			-- Initialisation des signaux
			etatc <= idlec;
			trameEnd <= '0';
			Ferr <= '0';
			OErr <= '0';
			DRdy <= '0';
			data <= (others => '0');
			data_reg <= (others => '0');
			
		elsif (rising_edge(clk)) then
			case etatc is
				when idlec =>					
					OErr <= '0';
					if (recep = '1') then
						-- On commence à recevoir
						cptBit := 10;			-- on repositionne le compteur
						parite := '0';			-- on repositionne la parité à 0
						parite_calc := '0';	-- on repositionne la parité calculée à 0
						etatc <= workingc;
					end if;

				when workingc =>
					-- On commence à recevoir
					if (tmpClk = '1') then
						-- On est prêt à recevoir
						if (3 <= cptBit) then
							-- On reçoit les bits de données utiles
							data_reg(cptBit - 3) <= tmpRxD;
							parite_calc := parite_calc xor tmpRxD; -- mise à jour de la parité
						elsif (cptBit = 2) then 
							-- Réception du bit de parité
							parite := tmpRxD;
						elsif (cptBit = 1) then
							-- Réception du bit de stop
							stop := tmpRxD;
							if ((parite /= parite_calc) or (stop = '0')) then
								-- Erreur de parité ou de bit de stop
								FErr <= '1';
							else
								-- Aucune erreur de parité ou de stop, on est prêt à recevoir à nouveau
								DRdy <= '1';
								data <= data_reg; -- On envoie la donnée
							end if;
							etatc <= endingc;
							trameEnd <= '1'; -- Réception de la trame terminée

						end if;
						cptBit := cptBit - 1;
					end if;

				when endingc =>
					-- La trame à été reçue
					-- Remise à zéro des erreurs
					data_reg <= (others => '0');
					trameEnd <= '0';
					FErr <= '0';
					DRdy <= '0';
					if (read = '0') then
						-- Erreur si l'on a pas réussi à lire la donnée
						OErr <= '1';
					end if;
					etatc <= idlec;
	
			end case;
		end if;
	end process;

end RxUnit_arch;

UART_emission/testRxUnit2.vhd
LIBRARY ieee;
USE ieee.std_logic_1164.ALL;
 
-- Uncomment the following library declaration if using
-- arithmetic functions with Signed or Unsigned values
--USE ieee.numeric_std.ALL;
 
ENTITY testRXUnit2 IS
END testRXUnit2;
 
ARCHITECTURE behavior OF testRXUnit2 IS 
 
    -- Component Declaration for the Unit Under Test (UUT)
 
    COMPONENT RxUnit
    PORT(
         clk : IN  std_logic;
         reset : IN  std_logic;
         enable : IN  std_logic;
         read : IN  std_logic;
         rxd : IN  std_logic;
         data : OUT  std_logic_vector(7 downto 0);
         Ferr : OUT  std_logic;
         OErr : OUT  std_logic;
         DRdy : OUT  std_logic
        );
    END COMPONENT;
    

   --Inputs
   signal clk : std_logic := '0';
   signal reset : std_logic := '0';
   signal enable : std_logic := '0';
   signal read : std_logic := '0';
   signal rxd : std_logic := '1';

 	--Outputs
   signal data : std_logic_vector(7 downto 0);
   signal Ferr : std_logic;
   signal OErr : std_logic;
   signal DRdy : std_logic;

   -- Clock period definitions
   constant clk_period : time := 25 ns;
 
BEGIN
 
	-- Instantiate the Unit Under Test (UUT)
   uut: RxUnit PORT MAP (
          clk => clk,
          reset => reset,
          enable => enable,
          read => read,
          rxd => rxd,
          data => data,
          Ferr => Ferr,
          OErr => OErr,
          DRdy => DRdy
        );

   -- Clock process definitions
   clk_process :process
   begin
		clk <= '0';
		wait for clk_period/2;
		clk <= '1';
		wait for clk_period/2;
   end process;
 
	enable <= clk;
   -- Stimulus process
   stim_proc: process
   begin	
		-- Simulation de transmission incorrecte : mauvais bit de parité
      reset <= '0';
      wait for 100 ns;	
			reset <= '1';
			
			wait for 20 ns;
			
			rxd <= '0';					-- bit de start
      wait for clk_period*16;
			rxd <= '1';					-- bit de donnée 1
      wait for clk_period*16;
			rxd <= '0';
      wait for clk_period*16;
			rxd <= '1';
      wait for clk_period*16;
			rxd <= '0';
      wait for clk_period*16;
			rxd <= '1';
      wait for clk_period*16;
			rxd <= '0';
      wait for clk_period*16;
			rxd <= '1';
      wait for clk_period*16;
			rxd <= '0';					-- bit de donnée 8
      wait for clk_period*16;
			rxd <= '1';					-- bit de parité
      wait for clk_period*16;
			rxd <= '1';					-- bit de stop
		wait for 264 ns;
			read <= '1';				-- lecture de la donnée par le processeur
		wait for clk_period*2;
			read <= '0';

      wait;
   end process;

END;

UART_emission/test2.vcd
$date
   Tue Jan 14 16:42:18 2025
$end
$version
  P.20131013
$end
$timescale
  1ps
$end
$scope module testrxunit2 $end
$var wire 1 1 clk $end
$var wire 1 2 reset $end
$var wire 1 3 enable $end
$var wire 1 4 read $end
$var wire 1 5 rxd $end
$var wire 1 = data [7] $end
$var wire 1 < data [6] $end
$var wire 1 ; data [5] $end
$var wire 1 : data [4] $end
$var wire 1 9 data [3] $end
$var wire 1 8 data [2] $end
$var wire 1 7 data [1] $end
$var wire 1 6 data [0] $end
$var wire 1 > ferr $end
$var wire 1 ? oerr $end
$var wire 1 @ drdy $end
$scope module uut $end
$var wire 1 1 clk $end
$var wire 1 2 reset $end
$var wire 1 3 enable $end
$var wire 1 4 read $end
$var wire 1 5 rxd $end
$var wire 1 = data [7] $end
$var wire 1 < data [6] $end
$var wire 1 ; data [5] $end
$var wire 1 : data [4] $end
$var wire 1 9 data [3] $end
$var wire 1 8 data [2] $end
$var wire 1 7 data [1] $end
$var wire 1 6 data [0] $end
$var wire 1 > ferr $end
$var wire 1 ? oerr $end
$var wire 1 @ drdy $end
$var wire 1 B tmprxd $end
$var wire 1 C tmpclk $end
$var wire 1 D trameend $end
$var wire 1 L data_reg [7] $end
$var wire 1 K data_reg [6] $end
$var wire 1 J data_reg [5] $end
$var wire 1 I data_reg [4] $end
$var wire 1 H data_reg [3] $end
$var wire 1 G data_reg [2] $end
$var wire 1 F data_reg [1] $end
$var wire 1 E data_reg [0] $end
$var wire 1 N recep $end
$upscope $end
$upscope $end
$enddefinitions $end
#0
$dumpvars
02
01
03
04
15
0=
0<
0;
0:
09
08
07
06
0>
0?
0@
1B
0C
0D
0L
0K
0J
0I
0H
0G
0F
0E
0N
$end
#12500
11
13
#25000
01
03
#37500
11
13
#50000
01
03
#62500
11
13
#75000
01
03
#87500
11
13
#100000
12
01
03
#112500
11
13
#120000
05
#125000
01
03
#137500
11
13
#150000
01
03
#162500
11
13
#175000
01
03
#187500
11
13
#200000
01
03
#212500
11
13
#225000
01
03
#237500
11
13
#250000
01
03
#262500
11
13
#275000
01
03
#287500
11
13
#300000
01
03
#312500
11
13
#325000
01
03
#337500
11
13
0B
1C
1N
#350000
01
03
#362500
11
13
0C
#375000
01
03
#387500
11
13
#400000
01
03
#412500
11
13
#425000
01
03
#437500
11
13
#450000
01
03
#462500
11
13
#475000
01
03
#487500
11
13
#500000
01
03
#512500
11
13
#520000
15
#525000
01
03
#537500
11
13
#550000
01
03
#562500
11
13
#575000
01
03
#587500
11
13
#600000
01
03
#612500
11
13
#625000
01
03
#637500
11
13
#650000
01
03
#662500
11
13
#675000
01
03
#687500
11
13
#700000
01
03
#712500
11
13
#725000
01
03
#737500
11
13
1B
1C
#750000
01
03
#762500
11
13
0C
1L
#775000
01
03
#787500
11
13
#800000
01
03
#812500
11
13
#825000
01
03
#837500
11
13
#850000
01
03
#862500
11
13
#875000
01
03
#887500
11
13
#900000
01
03
#912500
11
13
#920000
05
#925000
01
03
#937500
11
13
#950000
01
03
#962500
11
13
#975000
01
03
#987500
11
13
#1000000
01
03
#1012500
11
13
#1025000
01
03
#1037500
11
13
#1050000
01
03
#1062500
11
13
#1075000
01
03
#1087500
11
13
#1100000
01
03
#1112500
11
13
#1125000
01
03
#1137500
11
13
0B
1C
#1150000
01
03
#1162500
11
13
0C
#1175000
01
03
#1187500
11
13
#1200000
01
03
#1212500
11
13
#1225000
01
03
#1237500
11
13
#1250000
01
03
#1262500
11
13
#1275000
01
03
#1287500
11
13
#1300000
01
03
#1312500
11
13
#1320000
15
#1325000
01
03
#1337500
11
13
#1350000
01
03
#1362500
11
13
#1375000
01
03
#1387500
11
13
#1400000
01
03
#1412500
11
13
#1425000
01
03
#1437500
11
13
#1450000
01
03
#1462500
11
13
#1475000
01
03
#1487500
11
13
#1500000
01
03
#1512500
11
13
#1525000
01
03
#1537500
11
13
1B
1C
#1550000
01
03
#1562500
11
13
0C
1J
#1575000
01
03
#1587500
11
13
#1600000
01
03
#1612500
11
13
#1625000
01
03
#1637500
11
13
#1650000
01
03
#1662500
11
13
#1675000
01
03
#1687500
11
13
#1700000
01
03
#1712500
11
13
#1720000
05
#1725000
01
03
#1737500
11
13
#1750000
01
03
#1762500
11
13
#1775000
01
03
#1787500
11
13
#1800000
01
03
#1812500
11
13
#1825000
01
03
#1837500
11
13
#1850000
01
03
#1862500
11
13
#1875000
01
03
#1887500
11
13
#1900000
01
03
#1912500
11
13
#1925000
01
03
#1937500
11
13
0B
1C
#1950000
01
03
#1962500
11
13
0C
#1975000
01
03
#1987500
11
13
#2000000
01
03
#2012500
11
13
#2025000
01
03
#2037500
11
13
#2050000
01
03
#2062500
11
13
#2075000
01
03
#2087500
11
13
#2100000
01
03
#2112500
11
13
#2120000
15
#2125000
01
03
#2137500
11
13
#2150000
01
03
#2162500
11
13
#2175000
01
03
#2187500
11
13
#2200000
01
03
#2212500
11
13
#2225000
01
03
#2237500
11
13
#2250000
01
03
#2262500
11
13
#2275000
01
03
#2287500
11
13
#2300000
01
03
#2312500
11
13
#2325000
01
03
#2337500
11
13
1B
1C
#2350000
01
03
#2362500
11
13
0C
1H
#2375000
01
03
#2387500
11
13
#2400000
01
03
#2412500
11
13
#2425000
01
03
#2437500
11
13
#2450000
01
03
#2462500
11
13
#2475000
01
03
#2487500
11
13
#2500000
01
03
#2512500
11
13
#2520000
05
#2525000
01
03
#2537500
11
13
#2550000
01
03
#2562500
11
13
#2575000
01
03
#2587500
11
13
#2600000
01
03
#2612500
11
13
#2625000
01
03
#2637500
11
13
#2650000
01
03
#2662500
11
13
#2675000
01
03
#2687500
11
13
#2700000
01
03
#2712500
11
13
#2725000
01
03
#2737500
11
13
0B
1C
#2750000
01
03
#2762500
11
13
0C
#2775000
01
03
#2787500
11
13
#2800000
01
03
#2812500
11
13
#2825000
01
03
#2837500
11
13
#2850000
01
03
#2862500
11
13
#2875000
01
03
#2887500
11
13
#2900000
01
03
#2912500
11
13
#2920000
15
#2925000
01
03
#2937500
11
13
#2950000
01
03
#2962500
11
13
#2975000
01
03
#2987500
11
13
#3000000
01
03
#3012500
11
13
#3025000
01
03
#3037500
11
13
#3050000
01
03
#3062500
11
13
#3075000
01
03
#3087500
11
13
#3100000
01
03
#3112500
11
13
#3125000
01
03
#3137500
11
13
1B
1C
#3150000
01
03
#3162500
11
13
0C
1F
#3175000
01
03
#3187500
11
13
#3200000
01
03
#3212500
11
13
#3225000
01
03
#3237500
11
13
#3250000
01
03
#3262500
11
13
#3275000
01
03
#3287500
11
13
#3300000
01
03
#3312500
11
13
#3320000
05
#3325000
01
03
#3337500
11
13
#3350000
01
03
#3362500
11
13
#3375000
01
03
#3387500
11
13
#3400000
01
03
#3412500
11
13
#3425000
01
03
#3437500
11
13
#3450000
01
03
#3462500
11
13
#3475000
01
03
#3487500
11
13
#3500000
01
03
#3512500
11
13
#3525000
01
03
#3537500
11
13
0B
1C
#3550000
01
03
#3562500
11
13
0C
#3575000
01
03
#3587500
11
13
#3600000
01
03
#3612500
11
13
#3625000
01
03
#3637500
11
13
#3650000
01
03
#3662500
11
13
#3675000
01
03
#3687500
11
13
#3700000
01
03
#3712500
11
13
#3720000
15
#3725000
01
03
#3737500
11
13
#3750000
01
03
#3762500
11
13
#3775000
01
03
#3787500
11
13
#3800000
01
03
#3812500
11
13
#3825000
01
03
#3837500
11
13
#3850000
01
03
#3862500
11
13
#3875000
01
03
#3887500
11
13
#3900000
01
03
#3912500
11
13
#3925000
01
03
#3937500
11
13
1B
1C
#3950000
01
03
#3962500
11
13
0C
#3975000
01
03
#3987500
11
13
#4000000
01
03
#4012500
11
13
#4025000
01
03
#4037500
11
13
#4050000
01
03
#4062500
11
13
#4075000
01
03
#4087500
11
13
#4100000
01
03
#4112500
11
13
#4125000
01
03
#4137500
11
13
#4150000
01
03
#4162500
11
13
#4175000
01
03
#4187500
11
13
#4200000
01
03
#4212500
11
13
#4225000
01
03
#4237500
11
13
#4250000
01
03
#4262500
11
13
#4275000
01
03
#4287500
11
13
#4300000
01
03
#4312500
11
13
#4325000
01
03
#4337500
11
13
1C
#4350000
01
03
#4362500
11
13
1>
0C
1D
0N
#4375000
01
03
#4384000
14
#4387500
11
13
0>
0D
0L
0J
0H
0F
#4400000
01
03
#4412500
11
13
#4425000
01
03
#4434000
04
#4437500
11
13
#4450000
01
03
#4462500
11
13
#4475000
01
03
#4487500
11
13
#4500000
01
03
#4512500
11
13
#4525000
01
03
#4537500
11
13
#4550000
01
03
#4562500
11
13
#4575000
01
03
#4587500
11
13
#4600000
01
03
#4612500
11
13
#4625000
01
03
#4637500
11
13
#4650000
01
03
#4662500
11
13
#4675000
01
03
#4687500
11
13
#4700000
01
03
#4712500
11
13
#4725000
01
03
#4737500
11
13
#4750000
01
03
#4762500
11
13
#4775000
01
03
#4787500
11
13
#4800000
01
03
#4812500
11
13
#4825000
01
03
#4837500
11
13
#4850000
01
03
#4862500
11
13
#4875000
01
03
#4887500
11
13
#4900000
01
03
#4912500
11
13
#4925000
01
03
#4937500
11
13
#4950000
01
03
#4962500
11
13
#4975000
01
03
#4987500
11
13
#5000000
01
03
#5012500
11
13
#5025000
01
03
#5037500
11
13
#5050000
01
03
#5062500
11
13
#5075000
01
03
#5087500
11
13
#5100000
01
03
#5112500
11
13
#5125000
01
03
#5137500
11
13
#5150000
01
03
#5162500
11
13
#5175000
01
03
#5187500
11
13
#5200000
01
03
#5212500
11
13
#5225000
01
03
#5237500
11
13
#5250000
01
03
#5262500
11
13
#5275000
01
03
#5287500
11
13
#5300000
01
03
#5312500
11
13
#5325000
01
03
#5337500
11
13
#5350000
01
03
#5362500
11
13
#5375000
01
03
#5387500
11
13
#5400000
01
03
#5412500
11
13
#5425000
01
03
#5437500
11
13
#5450000
01
03
#5462500
11
13
#5475000
01
03
#5487500
11
13
#5500000
01
03
#5512500
11
13
#5525000
01
03
#5537500
11
13
#5550000
01
03
#5562500
11
13
#5575000
01
03
#5587500
11
13
#5600000
01
03
#5612500
11
13
#5625000
01
03
#5637500
11
13
#5650000
01
03
#5662500
11
13
#5675000
01
03
#5687500
11
13
#5700000
01
03
#5712500
11
13
#5725000
01
03
#5737500
11
13
#5750000
01
03
#5762500
11
13
#5775000
01
03
#5787500
11
13
#5800000
01
03
#5812500
11
13
#5825000
01
03
#5837500
11
13
#5850000
01
03
#5862500
11
13
#5875000
01
03
#5887500
11
13
#5900000
01
03
#5912500
11
13
#5925000
01
03
#5937500
11
13
#5950000
01
03
#5962500
11
13
#5975000
01
03
#5987500
11
13
#6000000
01
03
